rompy_swan/__init__.py
rompy_swan/boundary.py
rompy_swan/config.py
rompy_swan/data.py
rompy_swan/grid.py
rompy_swan/interface.py
rompy_swan/legacy.py
rompy_swan/types.py
rompy_swan/components/__init__.py
rompy_swan/components/base.py
rompy_swan/components/boundary.py
rompy_swan/components/cgrid.py
rompy_swan/components/group.py
rompy_swan/components/inpgrid.py
rompy_swan/components/lockup.py
rompy_swan/components/numerics.py
rompy_swan/components/output.py
rompy_swan/components/physics.py
rompy_swan/components/startup.py
rompy_swan/subcomponents/__init__.py
rompy_swan/subcomponents/base.py
rompy_swan/subcomponents/boundary.py
rompy_swan/subcomponents/numerics.py
rompy_swan/subcomponents/output.py
rompy_swan/subcomponents/physics.py
rompy_swan/subcomponents/readgrid.py
rompy_swan/subcomponents/spectrum.py
rompy_swan/subcomponents/startup.py
rompy_swan/subcomponents/time.py
rompy_swan/templates/swan/__init__.py
rompy_swan/templates/swan/{{runtime.staging_dir}}/INPUT
rompy_swan-0.8.0.dist-info/licenses/AUTHORS.rst
rompy_swan-0.8.0.dist-info/licenses/LICENSE
rompy_swan-0.8.0.dist-info/licenses/NOTICE
rompy_swan-0.8.0.dist-info/METADATA
rompy_swan-0.8.0.dist-info/WHEEL
rompy_swan-0.8.0.dist-info/entry_points.txt
rompy_swan-0.8.0.dist-info/top_level.txt
rompy_swan-0.8.0.dist-info/RECORD
