Metadata-Version: 2.4
Name: rompy-swan
Version: 0.8.0
Summary: SWAN wave model plugin for rompy
Author-email: Rompy Contributors <developers@rompy.com>
Maintainer-email: Rompy Contributors <developers@rompy.com>
License: Apache Software License 2.0
Project-URL: bugs, https://github.com/rom-py/rompy-swan/issues
Project-URL: changelog, https://github.com/rom-py/rompy-swan/blob/master/changelog.md
Project-URL: homepage, https://github.com/rom-py/rompy-swan
Classifier: Development Status :: 3 - Alpha
Classifier: Intended Audience :: Science/Research
Classifier: License :: OSI Approved :: Apache Software License
Classifier: Natural Language :: English
Classifier: Operating System :: OS Independent
Classifier: Topic :: Scientific/Engineering
Classifier: Topic :: Scientific/Engineering :: Physics
Classifier: Programming Language :: Python :: 3
Classifier: Programming Language :: Python :: 3.10
Classifier: Programming Language :: Python :: 3.11
Classifier: Programming Language :: Python :: 3.12
Requires-Python: >=3.10
License-File: LICENSE
License-File: NOTICE
License-File: AUTHORS.rst
Requires-Dist: rompy>=0.6
Requires-Dist: pydantic>2
Provides-Extra: dev
Requires-Dist: coverage; extra == "dev"
Requires-Dist: mypy; extra == "dev"
Requires-Dist: pytest; extra == "dev"
Requires-Dist: ruff; extra == "dev"
Requires-Dist: requests; extra == "dev"
Requires-Dist: envyaml; extra == "dev"
Provides-Extra: test
Requires-Dist: pytest; extra == "test"
Requires-Dist: coverage; extra == "test"
Requires-Dist: requests; extra == "test"
Requires-Dist: envyaml; extra == "test"
Provides-Extra: docs
Requires-Dist: mkdocs; extra == "docs"
Requires-Dist: mkdocs-material; extra == "docs"
Requires-Dist: mkdocstrings[python]; extra == "docs"
Dynamic: license-file
